ac_auto/__init__.py
ac_auto/ac_auto.py
ac_auto-0.1.2.dist-info/METADATA
ac_auto-0.1.2.dist-info/WHEEL
ac_auto-0.1.2.dist-info/top_level.txt
ac_auto-0.1.2.dist-info/RECORD
