Metadata-Version: 2.1
Name: ac_auto
Version: 0.1.2
Summary: 文本多模匹配AC自动机的Python实现
Home-page: 
Author: ray.ping
Author-email: 342099577@qq.com
License: MIT
Requires-Dist: jieba >=0.42.1
